buildnis/__main__.py
buildnis/config/OS_ARCH_COMPILER_BUILDTYPE.json
buildnis/config/module_config.json
buildnis/config/project_config.json
buildnis/config/project_dependency_config.json
buildnis/configure_scripts/template.bat
buildnis/configure_scripts/template.sh
buildnis/configure_scripts/Linux/amd.sh
buildnis/configure_scripts/Linux/clang.sh
buildnis/configure_scripts/Linux/doxygen.sh
buildnis/configure_scripts/Linux/gcc.sh
buildnis/configure_scripts/Linux/intel.sh
buildnis/configure_scripts/Linux/java.sh
buildnis/configure_scripts/Linux/nvidia.sh
buildnis/configure_scripts/Linux/python.sh
buildnis/configure_scripts/Linux/python38.sh
buildnis/configure_scripts/Linux/python39.sh
buildnis/configure_scripts/Linux/sphinx.sh
buildnis/configure_scripts/OSX/JavaVM.sh
buildnis/configure_scripts/OSX/clang.sh
buildnis/configure_scripts/OSX/doxygen.sh
buildnis/configure_scripts/OSX/intel.sh
buildnis/configure_scripts/OSX/pythonint.sh
buildnis/configure_scripts/OSX/sphinx.sh
buildnis/configure_scripts/Windows/Intel.bat
buildnis/configure_scripts/Windows/JavaVM.bat
buildnis/configure_scripts/Windows/VisualStudio.bat
buildnis/configure_scripts/Windows/doxygenDoc.bat
buildnis/configure_scripts/Windows/pythonInt.bat
buildnis/configure_scripts/Windows/sphinx.bat
buildnis/doc/doctrees/commandline.doctree
buildnis/doc/doctrees/configuration.doctree
buildnis/doc/doctrees/customizing.doctree
buildnis/doc/doctrees/dev_index.doctree
buildnis/doc/doctrees/environment.pickle
buildnis/doc/doctrees/extending.doctree
buildnis/doc/doctrees/genindex.doctree
buildnis/doc/doctrees/index.doctree
buildnis/doc/doctrees/license.doctree
buildnis/doc/doctrees/modules.builds.doctree
buildnis/doc/doctrees/modules.config.doctree
buildnis/doc/doctrees/modules.doctree
buildnis/doc/doctrees/modules.helpers.doctree
buildnis/doc/doctrees/py-modindex.doctree
buildnis/doc/doctrees/stages.doctree
buildnis/doc/doctrees/supported_configs.doctree
buildnis/doc/doctrees/usage.doctree
buildnis/doc/html/.buildinfo
buildnis-0.1.11.dist-info/LICENSE
buildnis-0.1.11.dist-info/METADATA
buildnis-0.1.11.dist-info/WHEEL
buildnis-0.1.11.dist-info/entry_points.txt
buildnis-0.1.11.dist-info/top_level.txt
buildnis-0.1.11.dist-info/RECORD
