Metadata-Version: 2.1
Name: buildnis
Version: 0.1.11
Summary: A distributed, platform independent build system that can handle C++20 modules and Fortran modules (and should be flexible enough to build anything else).
Home-page: https://github.com/Release-Candidate/Buildnis
Author: Release-Candidate
Author-email: rec@gmx.at
License: UNKNOWN
Project-URL: Bug Tracker, https://github.com/Release-Candidate/Buildnis/issues
Project-URL: Documentation, https://buildnis.readthedocs.io/en/latest/
Keywords: build,build system,C++,Fortran
Platform: UNKNOWN
Classifier: Programming Language :: Python :: 3 :: Only
Classifier: Programming Language :: Python :: 3.9
Classifier: License :: OSI Approved :: MIT License
Classifier: Operating System :: MacOS :: MacOS X
Classifier: Operating System :: Microsoft :: Windows
Classifier: Operating System :: POSIX :: Linux
Classifier: Operating System :: OS Independent
Classifier: Topic :: Software Development :: Build Tools
Classifier: Intended Audience :: Developers
Classifier: Environment :: Console
Classifier: Development Status :: 2 - Pre-Alpha
Requires-Python: >=3.9
